monistode_assembler/__init__.py
monistode_assembler/arguments/__init__.py
monistode_assembler/arguments/address.py
monistode_assembler/arguments/common.py
monistode_assembler/arguments/immediate.py
monistode_assembler/arguments/label.py
monistode_assembler/arguments/matching_parser.py
monistode_assembler/arguments/padding.py
monistode_assembler/arguments/regiser.py
monistode_assembler/arguments/register_address.py
monistode_assembler/arguments/register_address_offset.py
monistode_assembler/arguments/register_offset.py
monistode_assembler/arguments/string.py
monistode_assembler/assemble.py
monistode_assembler/cli.py
monistode_assembler/command.py
monistode_assembler/command_description.py
monistode_assembler/description.py
monistode_assembler/disassemble.py
monistode_assembler/disassemble_text.py
monistode_assembler/exceptions.py
monistode_assembler/parse.py
monistode_assembler/py.typed
monistode_assembler/sections/__init__.py
monistode_assembler/sections/common.py
monistode_assembler/sections/data.py
monistode_assembler/sections/data_argument.py
monistode_assembler/sections/text.py
monistode_assembler/sections/text_argument.py
monistode_assembler-0.1.25.dist-info/METADATA
monistode_assembler-0.1.25.dist-info/WHEEL
monistode_assembler-0.1.25.dist-info/entry_points.txt
monistode_assembler-0.1.25.dist-info/RECORD
